morphostain/__init__.py
morphostain/morphostain.py
morphostain/hasel/__init__.py
morphostain/resources/alcian_blue_h.json
morphostain/resources/dab.json
morphostain/resources/dab_2.json
morphostain-1.0.8.dist-info/METADATA
morphostain-1.0.8.dist-info/RECORD
morphostain-1.0.8.dist-info/WHEEL
morphostain-1.0.8.dist-info/entry_points.txt
morphostain-1.0.8.dist-info/top_level.txt
